LICENSE
montydb/__init__.py
montydb/_version.py
montydb/base.py
montydb/client.py
montydb/collection.py
montydb/configure.py
montydb/cursor.py
montydb/database.py
montydb/engine/__init__.py
montydb/engine/field_walker.py
montydb/engine/project.py
montydb/engine/queries.py
montydb/engine/update.py
montydb/engine/weighted.py
montydb/errors.py
montydb/results.py
montydb/storage/__init__.py
montydb/storage/flatfile.py
montydb/storage/lightning.py
montydb/storage/memory.py
montydb/storage/sqlite.py
montydb/types/__init__.py
montydb/types/_bson.py
montydb/types/_nobson.py
montydb/types/bson.py
montydb/types/compat.py
montydb/types/helper.py
montydb/types/objectid.py
montydb/types/tz_util.py
montydb/utils/__init__.py
montydb/utils/io.py
montydb/utils/mt_list.py
montydb-2.5.4.dist-info/METADATA
montydb-2.5.4.dist-info/LICENSE
montydb-2.5.4.dist-info/WHEEL
montydb-2.5.4.dist-info/RECORD
