Metadata-Version: 2.1
Name: montydb
Version: 2.5.4
Summary: Monty, Mongo tinified. MongoDB implemented in Python !
Home-page: https://github.com/davidlatwe/montydb
License: BSD-3-Clause License
Keywords: monty,montydb,pymongo,mongodb,database,embedded
Author: davidlatwe
Author-email: davidlatwe@gmail.com
Requires-Python: >=3.7
Classifier: Intended Audience :: Developers
Classifier: License :: OSI Approved :: BSD License
Classifier: License :: Other/Proprietary License
Classifier: Operating System :: OS Independent
Classifier: Programming Language :: Python
Classifier: Programming Language :: Python :: 3
Classifier: Programming Language :: Python :: 3.7
Classifier: Programming Language :: Python :: 3.8
Classifier: Programming Language :: Python :: 3.9
Classifier: Programming Language :: Python :: 3.10
Classifier: Programming Language :: Python :: 3.11
Classifier: Programming Language :: Python :: 3.10
Classifier: Programming Language :: Python :: 3.11
Classifier: Programming Language :: Python :: 3.12
Classifier: Programming Language :: Python :: 3.7
Classifier: Programming Language :: Python :: 3.8
Classifier: Programming Language :: Python :: 3.9
Classifier: Topic :: Database
Classifier: Topic :: Database :: Database Engines/Servers
Project-URL: Repository, https://github.com/davidlatwe/montydb
